{"totalVideos": 19993, "dateRange": {"earliest": "2014-03-10", "latest": "2026-04-07"}, "totalDays": 4411, "avgPerDay": 4.5, "uniqueChannels": 3449, "monthly": [{"month": "2014-03", "count": 1}, {"month": "2014-04", "count": 1}, {"month": "2014-07", "count": 1}, {"month": "2014-08", "count": 29}, {"month": "2014-09", "count": 5}, {"month": "2014-10", "count": 3}, {"month": "2014-11", "count": 148}, {"month": "2014-12", "count": 114}, {"month": "2015-01", "count": 85}, {"month": "2015-03", "count": 13}, {"month": "2015-10", "count": 14}, {"month": "2015-11", "count": 2}, {"month": "2015-12", "count": 1}, {"month": "2016-01", "count": 2}, {"month": "2016-02", "count": 47}, {"month": "2016-04", "count": 1}, {"month": "2016-05", "count": 3}, {"month": "2016-06", "count": 1}, {"month": "2016-07", "count": 38}, {"month": "2016-08", "count": 21}, {"month": "2016-09", "count": 63}, {"month": "2016-10", "count": 26}, {"month": "2016-11", "count": 162}, {"month": "2016-12", "count": 40}, {"month": "2017-01", "count": 14}, {"month": "2017-02", "count": 28}, {"month": "2017-03", "count": 12}, {"month": "2017-04", "count": 16}, {"month": "2017-05", "count": 2}, {"month": "2017-06", "count": 72}, {"month": "2017-07", "count": 73}, {"month": "2017-08", "count": 28}, {"month": "2017-09", "count": 16}, {"month": "2017-10", "count": 33}, {"month": "2017-11", "count": 47}, {"month": "2017-12", "count": 2}, {"month": "2022-04", "count": 3}, {"month": "2023-05", "count": 1}, {"month": "2023-06", "count": 7}, {"month": "2023-07", "count": 4}, {"month": "2023-08", "count": 23}, {"month": "2024-04", "count": 463}, {"month": "2024-05", "count": 763}, {"month": "2024-06", "count": 966}, {"month": "2024-07", "count": 921}, {"month": "2024-08", "count": 783}, {"month": "2024-09", "count": 552}, {"month": "2024-10", "count": 673}, {"month": "2024-11", "count": 960}, {"month": "2024-12", "count": 845}, {"month": "2025-01", "count": 510}, {"month": "2025-02", "count": 723}, {"month": "2025-03", "count": 851}, {"month": "2025-04", "count": 939}, {"month": "2025-05", "count": 708}, {"month": "2025-06", "count": 592}, {"month": "2025-07", "count": 554}, {"month": "2025-08", "count": 605}, {"month": "2025-09", "count": 676}, {"month": "2025-10", "count": 1217}, {"month": "2025-11", "count": 883}, {"month": "2025-12", "count": 297}, {"month": "2026-01", "count": 861}, {"month": "2026-02", "count": 969}, {"month": "2026-03", "count": 1187}, {"month": "2026-04", "count": 293}], "clusters": [{"id": "chinese_pop_music", "label": "Chinese Pop Music", "count": 8980, "recent90d": 1532, "monthly": [{"month": "2014-03", "count": 0}, {"month": "2014-04", "count": 0}, {"month": "2014-07", "count": 0}, {"month": "2014-08", "count": 0}, {"month": "2014-09", "count": 0}, {"month": "2014-10", "count": 0}, {"month": "2014-11", "count": 0}, {"month": "2014-12", "count": 0}, {"month": "2015-01", "count": 0}, {"month": "2015-03", "count": 2}, {"month": "2015-10", "count": 0}, {"month": "2015-11", "count": 0}, {"month": "2015-12", "count": 0}, {"month": "2016-01", "count": 0}, {"month": "2016-02", "count": 0}, {"month": "2016-04", "count": 0}, {"month": "2016-05", "count": 0}, {"month": "2016-06", "count": 0}, {"month": "2016-07", "count": 1}, {"month": "2016-08", "count": 0}, {"month": "2016-09", "count": 0}, {"month": "2016-10", "count": 0}, {"month": "2016-11", "count": 1}, {"month": "2016-12", "count": 0}, {"month": "2017-01", "count": 0}, {"month": "2017-02", "count": 0}, {"month": "2017-03", "count": 0}, {"month": "2017-04", "count": 0}, {"month": "2017-05", "count": 0}, {"month": "2017-06", "count": 0}, {"month": "2017-07", "count": 0}, {"month": "2017-08", "count": 0}, {"month": "2017-09", "count": 3}, {"month": "2017-10", "count": 0}, {"month": "2017-11", "count": 0}, {"month": "2017-12", "count": 0}, {"month": "2022-04", "count": 0}, {"month": "2023-05", "count": 0}, {"month": "2023-06", "count": 0}, {"month": "2023-07", "count": 0}, {"month": "2023-08", "count": 1}, {"month": "2024-04", "count": 260}, {"month": "2024-05", "count": 332}, {"month": "2024-06", "count": 588}, {"month": "2024-07", "count": 527}, {"month": "2024-08", "count": 388}, {"month": "2024-09", "count": 242}, {"month": "2024-10", "count": 323}, {"month": "2024-11", "count": 303}, {"month": "2024-12", "count": 275}, {"month": "2025-01", "count": 196}, {"month": "2025-02", "count": 440}, {"month": "2025-03", "count": 561}, {"month": "2025-04", "count": 628}, {"month": "2025-05", "count": 529}, {"month": "2025-06", "count": 162}, {"month": "2025-07", "count": 191}, {"month": "2025-08", "count": 131}, {"month": "2025-09", "count": 313}, {"month": "2025-10", "count": 404}, {"month": "2025-11", "count": 431}, {"month": "2025-12", "count": 154}, {"month": "2026-01", "count": 381}, {"month": "2026-02", "count": 489}, {"month": "2026-03", "count": 552}, {"month": "2026-04", "count": 172}]}, {"id": "other", "label": "Other / Uncategorized", "count": 8415, "recent90d": 1323, "monthly": [{"month": "2014-03", "count": 1}, {"month": "2014-04", "count": 1}, {"month": "2014-07", "count": 1}, {"month": "2014-08", "count": 29}, {"month": "2014-09", "count": 5}, {"month": "2014-10", "count": 3}, {"month": "2014-11", "count": 146}, {"month": "2014-12", "count": 108}, {"month": "2015-01", "count": 83}, {"month": "2015-03", "count": 11}, {"month": "2015-10", "count": 14}, {"month": "2015-11", "count": 2}, {"month": "2015-12", "count": 1}, {"month": "2016-01", "count": 2}, {"month": "2016-02", "count": 47}, {"month": "2016-04", "count": 1}, {"month": "2016-05", "count": 3}, {"month": "2016-06", "count": 1}, {"month": "2016-07", "count": 37}, {"month": "2016-08", "count": 21}, {"month": "2016-09", "count": 62}, {"month": "2016-10", "count": 26}, {"month": "2016-11", "count": 150}, {"month": "2016-12", "count": 39}, {"month": "2017-01", "count": 14}, {"month": "2017-02", "count": 28}, {"month": "2017-03", "count": 12}, {"month": "2017-04", "count": 6}, {"month": "2017-05", "count": 2}, {"month": "2017-06", "count": 72}, {"month": "2017-07", "count": 50}, {"month": "2017-08", "count": 28}, {"month": "2017-09", "count": 10}, {"month": "2017-10", "count": 23}, {"month": "2017-11", "count": 43}, {"month": "2017-12", "count": 2}, {"month": "2022-04", "count": 3}, {"month": "2023-05", "count": 1}, {"month": "2023-06", "count": 6}, {"month": "2023-07", "count": 3}, {"month": "2023-08", "count": 20}, {"month": "2024-04", "count": 154}, {"month": "2024-05", "count": 270}, {"month": "2024-06", "count": 279}, {"month": "2024-07", "count": 289}, {"month": "2024-08", "count": 311}, {"month": "2024-09", "count": 225}, {"month": "2024-10", "count": 219}, {"month": "2024-11", "count": 504}, {"month": "2024-12", "count": 460}, {"month": "2025-01", "count": 254}, {"month": "2025-02", "count": 222}, {"month": "2025-03", "count": 233}, {"month": "2025-04", "count": 224}, {"month": "2025-05", "count": 117}, {"month": "2025-06", "count": 100}, {"month": "2025-07", "count": 272}, {"month": "2025-08", "count": 347}, {"month": "2025-09", "count": 267}, {"month": "2025-10", "count": 673}, {"month": "2025-11", "count": 381}, {"month": "2025-12", "count": 124}, {"month": "2026-01", "count": 370}, {"month": "2026-02", "count": 372}, {"month": "2026-03", "count": 531}, {"month": "2026-04", "count": 100}]}, {"id": "ml_ai", "label": "Machine Learning / AI", "count": 858, "recent90d": 100, "monthly": [{"month": "2014-03", "count": 0}, {"month": "2014-04", "count": 0}, {"month": "2014-07", "count": 0}, {"month": "2014-08", "count": 0}, {"month": "2014-09", "count": 0}, {"month": "2014-10", "count": 0}, {"month": "2014-11", "count": 0}, {"month": "2014-12", "count": 1}, {"month": "2015-01", "count": 0}, {"month": "2015-03", "count": 0}, {"month": "2015-10", "count": 0}, {"month": "2015-11", "count": 0}, {"month": "2015-12", "count": 0}, {"month": "2016-01", "count": 0}, {"month": "2016-02", "count": 0}, {"month": "2016-04", "count": 0}, {"month": "2016-05", "count": 0}, {"month": "2016-06", "count": 0}, {"month": "2016-07", "count": 0}, {"month": "2016-08", "count": 0}, {"month": "2016-09", "count": 0}, {"month": "2016-10", "count": 0}, {"month": "2016-11", "count": 3}, {"month": "2016-12", "count": 0}, {"month": "2017-01", "count": 0}, {"month": "2017-02", "count": 0}, {"month": "2017-03", "count": 0}, {"month": "2017-04", "count": 10}, {"month": "2017-05", "count": 0}, {"month": "2017-06", "count": 0}, {"month": "2017-07", "count": 1}, {"month": "2017-08", "count": 0}, {"month": "2017-09", "count": 3}, {"month": "2017-10", "count": 10}, {"month": "2017-11", "count": 4}, {"month": "2017-12", "count": 0}, {"month": "2022-04", "count": 0}, {"month": "2023-05", "count": 0}, {"month": "2023-06", "count": 1}, {"month": "2023-07", "count": 0}, {"month": "2023-08", "count": 1}, {"month": "2024-04", "count": 22}, {"month": "2024-05", "count": 81}, {"month": "2024-06", "count": 39}, {"month": "2024-07", "count": 23}, {"month": "2024-08", "count": 27}, {"month": "2024-09", "count": 28}, {"month": "2024-10", "count": 37}, {"month": "2024-11", "count": 52}, {"month": "2024-12", "count": 19}, {"month": "2025-01", "count": 2}, {"month": "2025-02", "count": 19}, {"month": "2025-03", "count": 30}, {"month": "2025-04", "count": 38}, {"month": "2025-05", "count": 22}, {"month": "2025-06", "count": 21}, {"month": "2025-07", "count": 47}, {"month": "2025-08", "count": 58}, {"month": "2025-09", "count": 60}, {"month": "2025-10", "count": 76}, {"month": "2025-11", "count": 19}, {"month": "2025-12", "count": 3}, {"month": "2026-01", "count": 30}, {"month": "2026-02", "count": 40}, {"month": "2026-03", "count": 16}, {"month": "2026-04", "count": 15}]}, {"id": "chinese_news_commentary", "label": "Chinese News & Commentary", "count": 544, "recent90d": 140, "monthly": [{"month": "2014-03", "count": 0}, {"month": "2014-04", "count": 0}, {"month": "2014-07", "count": 0}, {"month": "2014-08", "count": 0}, {"month": "2014-09", "count": 0}, {"month": "2014-10", "count": 0}, {"month": "2014-11", "count": 2}, {"month": "2014-12", "count": 0}, {"month": "2015-01", "count": 0}, {"month": "2015-03", "count": 0}, {"month": "2015-10", "count": 0}, {"month": "2015-11", "count": 0}, {"month": "2015-12", "count": 0}, {"month": "2016-01", "count": 0}, {"month": "2016-02", "count": 0}, {"month": "2016-04", "count": 0}, {"month": "2016-05", "count": 0}, {"month": "2016-06", "count": 0}, {"month": "2016-07", "count": 0}, {"month": "2016-08", "count": 0}, {"month": "2016-09", "count": 0}, {"month": "2016-10", "count": 0}, {"month": "2016-11", "count": 0}, {"month": "2016-12", "count": 1}, {"month": "2017-01", "count": 0}, {"month": "2017-02", "count": 0}, {"month": "2017-03", "count": 0}, {"month": "2017-04", "count": 0}, {"month": "2017-05", "count": 0}, {"month": "2017-06", "count": 0}, {"month": "2017-07", "count": 16}, {"month": "2017-08", "count": 0}, {"month": "2017-09", "count": 0}, {"month": "2017-10", "count": 0}, {"month": "2017-11", "count": 0}, {"month": "2017-12", "count": 0}, {"month": "2022-04", "count": 0}, {"month": "2023-05", "count": 0}, {"month": "2023-06", "count": 0}, {"month": "2023-07", "count": 1}, {"month": "2023-08", "count": 0}, {"month": "2024-04", "count": 9}, {"month": "2024-05", "count": 26}, {"month": "2024-06", "count": 31}, {"month": "2024-07", "count": 21}, {"month": "2024-08", "count": 21}, {"month": "2024-09", "count": 8}, {"month": "2024-10", "count": 4}, {"month": "2024-11", "count": 17}, {"month": "2024-12", "count": 11}, {"month": "2025-01", "count": 11}, {"month": "2025-02", "count": 25}, {"month": "2025-03", "count": 5}, {"month": "2025-04", "count": 14}, {"month": "2025-05", "count": 17}, {"month": "2025-06", "count": 4}, {"month": "2025-07", "count": 9}, {"month": "2025-08", "count": 26}, {"month": "2025-09", "count": 17}, {"month": "2025-10", "count": 35}, {"month": "2025-11", "count": 46}, {"month": "2025-12", "count": 12}, {"month": "2026-01", "count": 61}, {"month": "2026-02", "count": 34}, {"month": "2026-03", "count": 55}, {"month": "2026-04", "count": 5}]}, {"id": "kids_family", "label": "Kids / Family", "count": 319, "recent90d": 1, "monthly": [{"month": "2014-03", "count": 0}, {"month": "2014-04", "count": 0}, {"month": "2014-07", "count": 0}, {"month": "2014-08", "count": 0}, {"month": "2014-09", "count": 0}, {"month": "2014-10", "count": 0}, {"month": "2014-11", "count": 0}, {"month": "2014-12", "count": 5}, {"month": "2015-01", "count": 2}, {"month": "2015-03", "count": 0}, {"month": "2015-10", "count": 0}, {"month": "2015-11", "count": 0}, {"month": "2015-12", "count": 0}, {"month": "2016-01", "count": 0}, {"month": "2016-02", "count": 0}, {"month": "2016-04", "count": 0}, {"month": "2016-05", "count": 0}, {"month": "2016-06", "count": 0}, {"month": "2016-07", "count": 0}, {"month": "2016-08", "count": 0}, {"month": "2016-09", "count": 0}, {"month": "2016-10", "count": 0}, {"month": "2016-11", "count": 2}, {"month": "2016-12", "count": 0}, {"month": "2017-01", "count": 0}, {"month": "2017-02", "count": 0}, {"month": "2017-03", "count": 0}, {"month": "2017-04", "count": 0}, {"month": "2017-05", "count": 0}, {"month": "2017-06", "count": 0}, {"month": "2017-07", "count": 0}, {"month": "2017-08", "count": 0}, {"month": "2017-09", "count": 0}, {"month": "2017-10", "count": 0}, {"month": "2017-11", "count": 0}, {"month": "2017-12", "count": 0}, {"month": "2022-04", "count": 0}, {"month": "2023-05", "count": 0}, {"month": "2023-06", "count": 0}, {"month": "2023-07", "count": 0}, {"month": "2023-08", "count": 0}, {"month": "2024-04", "count": 0}, {"month": "2024-05", "count": 0}, {"month": "2024-06", "count": 1}, {"month": "2024-07", "count": 0}, {"month": "2024-08", "count": 3}, {"month": "2024-09", "count": 2}, {"month": "2024-10", "count": 0}, {"month": "2024-11", "count": 0}, {"month": "2024-12", "count": 2}, {"month": "2025-01", "count": 2}, {"month": "2025-02", "count": 7}, {"month": "2025-03", "count": 8}, {"month": "2025-04", "count": 0}, {"month": "2025-05", "count": 0}, {"month": "2025-06", "count": 281}, {"month": "2025-07", "count": 0}, {"month": "2025-08", "count": 0}, {"month": "2025-09", "count": 0}, {"month": "2025-10", "count": 3}, {"month": "2025-11", "count": 0}, {"month": "2025-12", "count": 0}, {"month": "2026-01", "count": 0}, {"month": "2026-02", "count": 0}, {"month": "2026-03", "count": 1}, {"month": "2026-04", "count": 0}]}, {"id": "cpp_systems", "label": "C++ & Systems Programming", "count": 317, "recent90d": 6, "monthly": [{"month": "2014-03", "count": 0}, {"month": "2014-04", "count": 0}, {"month": "2014-07", "count": 0}, {"month": "2014-08", "count": 0}, {"month": "2014-09", "count": 0}, {"month": "2014-10", "count": 0}, {"month": "2014-11", "count": 0}, {"month": "2014-12", "count": 0}, {"month": "2015-01", "count": 0}, {"month": "2015-03", "count": 0}, {"month": "2015-10", "count": 0}, {"month": "2015-11", "count": 0}, {"month": "2015-12", "count": 0}, {"month": "2016-01", "count": 0}, {"month": "2016-02", "count": 0}, {"month": "2016-04", "count": 0}, {"month": "2016-05", "count": 0}, {"month": "2016-06", "count": 0}, {"month": "2016-07", "count": 0}, {"month": "2016-08", "count": 0}, {"month": "2016-09", "count": 0}, {"month": "2016-10", "count": 0}, {"month": "2016-11", "count": 0}, {"month": "2016-12", "count": 0}, {"month": "2017-01", "count": 0}, {"month": "2017-02", "count": 0}, {"month": "2017-03", "count": 0}, {"month": "2017-04", "count": 0}, {"month": "2017-05", "count": 0}, {"month": "2017-06", "count": 0}, {"month": "2017-07", "count": 1}, {"month": "2017-08", "count": 0}, {"month": "2017-09", "count": 0}, {"month": "2017-10", "count": 0}, {"month": "2017-11", "count": 0}, {"month": "2017-12", "count": 0}, {"month": "2022-04", "count": 0}, {"month": "2023-05", "count": 0}, {"month": "2023-06", "count": 0}, {"month": "2023-07", "count": 0}, {"month": "2023-08", "count": 0}, {"month": "2024-04", "count": 0}, {"month": "2024-05", "count": 0}, {"month": "2024-06", "count": 0}, {"month": "2024-07", "count": 32}, {"month": "2024-08", "count": 5}, {"month": "2024-09", "count": 24}, {"month": "2024-10", "count": 76}, {"month": "2024-11", "count": 62}, {"month": "2024-12", "count": 63}, {"month": "2025-01", "count": 39}, {"month": "2025-02", "count": 1}, {"month": "2025-03", "count": 5}, {"month": "2025-04", "count": 2}, {"month": "2025-05", "count": 1}, {"month": "2025-06", "count": 0}, {"month": "2025-07", "count": 0}, {"month": "2025-08", "count": 0}, {"month": "2025-09", "count": 0}, {"month": "2025-10", "count": 0}, {"month": "2025-11", "count": 0}, {"month": "2025-12", "count": 0}, {"month": "2026-01", "count": 0}, {"month": "2026-02", "count": 5}, {"month": "2026-03", "count": 1}, {"month": "2026-04", "count": 0}]}, {"id": "scientific_computing", "label": "Scientific Computing & Math", "count": 173, "recent90d": 25, "monthly": [{"month": "2014-03", "count": 0}, {"month": "2014-04", "count": 0}, {"month": "2014-07", "count": 0}, {"month": "2014-08", "count": 0}, {"month": "2014-09", "count": 0}, {"month": "2014-10", "count": 0}, {"month": "2014-11", "count": 0}, {"month": "2014-12", "count": 0}, {"month": "2015-01", "count": 0}, {"month": "2015-03", "count": 0}, {"month": "2015-10", "count": 0}, {"month": "2015-11", "count": 0}, {"month": "2015-12", "count": 0}, {"month": "2016-01", "count": 0}, {"month": "2016-02", "count": 0}, {"month": "2016-04", "count": 0}, {"month": "2016-05", "count": 0}, {"month": "2016-06", "count": 0}, {"month": "2016-07", "count": 0}, {"month": "2016-08", "count": 0}, {"month": "2016-09", "count": 1}, {"month": "2016-10", "count": 0}, {"month": "2016-11", "count": 6}, {"month": "2016-12", "count": 0}, {"month": "2017-01", "count": 0}, {"month": "2017-02", "count": 0}, {"month": "2017-03", "count": 0}, {"month": "2017-04", "count": 0}, {"month": "2017-05", "count": 0}, {"month": "2017-06", "count": 0}, {"month": "2017-07", "count": 4}, {"month": "2017-08", "count": 0}, {"month": "2017-09", "count": 0}, {"month": "2017-10", "count": 0}, {"month": "2017-11", "count": 0}, {"month": "2017-12", "count": 0}, {"month": "2022-04", "count": 0}, {"month": "2023-05", "count": 0}, {"month": "2023-06", "count": 0}, {"month": "2023-07", "count": 0}, {"month": "2023-08", "count": 0}, {"month": "2024-04", "count": 0}, {"month": "2024-05", "count": 0}, {"month": "2024-06", "count": 0}, {"month": "2024-07", "count": 0}, {"month": "2024-08", "count": 0}, {"month": "2024-09", "count": 0}, {"month": "2024-10", "count": 0}, {"month": "2024-11", "count": 0}, {"month": "2024-12", "count": 1}, {"month": "2025-01", "count": 0}, {"month": "2025-02", "count": 0}, {"month": "2025-03", "count": 1}, {"month": "2025-04", "count": 24}, {"month": "2025-05", "count": 18}, {"month": "2025-06", "count": 22}, {"month": "2025-07", "count": 27}, {"month": "2025-08", "count": 29}, {"month": "2025-09", "count": 12}, {"month": "2025-10", "count": 3}, {"month": "2025-11", "count": 0}, {"month": "2025-12", "count": 0}, {"month": "2026-01", "count": 4}, {"month": "2026-02", "count": 5}, {"month": "2026-03", "count": 16}, {"month": "2026-04", "count": 0}]}, {"id": "chinese_variety_tv", "label": "Chinese Variety TV", "count": 163, "recent90d": 23, "monthly": [{"month": "2014-03", "count": 0}, {"month": "2014-04", "count": 0}, {"month": "2014-07", "count": 0}, {"month": "2014-08", "count": 0}, {"month": "2014-09", "count": 0}, {"month": "2014-10", "count": 0}, {"month": "2014-11", "count": 0}, {"month": "2014-12", "count": 0}, {"month": "2015-01", "count": 0}, {"month": "2015-03", "count": 0}, {"month": "2015-10", "count": 0}, {"month": "2015-11", "count": 0}, {"month": "2015-12", "count": 0}, {"month": "2016-01", "count": 0}, {"month": "2016-02", "count": 0}, {"month": "2016-04", "count": 0}, {"month": "2016-05", "count": 0}, {"month": "2016-06", "count": 0}, {"month": "2016-07", "count": 0}, {"month": "2016-08", "count": 0}, {"month": "2016-09", "count": 0}, {"month": "2016-10", "count": 0}, {"month": "2016-11", "count": 0}, {"month": "2016-12", "count": 0}, {"month": "2017-01", "count": 0}, {"month": "2017-02", "count": 0}, {"month": "2017-03", "count": 0}, {"month": "2017-04", "count": 0}, {"month": "2017-05", "count": 0}, {"month": "2017-06", "count": 0}, {"month": "2017-07", "count": 1}, {"month": "2017-08", "count": 0}, {"month": "2017-09", "count": 0}, {"month": "2017-10", "count": 0}, {"month": "2017-11", "count": 0}, {"month": "2017-12", "count": 0}, {"month": "2022-04", "count": 0}, {"month": "2023-05", "count": 0}, {"month": "2023-06", "count": 0}, {"month": "2023-07", "count": 0}, {"month": "2023-08", "count": 0}, {"month": "2024-04", "count": 16}, {"month": "2024-05", "count": 38}, {"month": "2024-06", "count": 19}, {"month": "2024-07", "count": 22}, {"month": "2024-08", "count": 7}, {"month": "2024-09", "count": 6}, {"month": "2024-10", "count": 4}, {"month": "2024-11", "count": 17}, {"month": "2024-12", "count": 3}, {"month": "2025-01", "count": 1}, {"month": "2025-02", "count": 0}, {"month": "2025-03", "count": 1}, {"month": "2025-04", "count": 0}, {"month": "2025-05", "count": 3}, {"month": "2025-06", "count": 0}, {"month": "2025-07", "count": 0}, {"month": "2025-08", "count": 0}, {"month": "2025-09", "count": 0}, {"month": "2025-10", "count": 2}, {"month": "2025-11", "count": 0}, {"month": "2025-12", "count": 0}, {"month": "2026-01", "count": 0}, {"month": "2026-02", "count": 16}, {"month": "2026-03", "count": 7}, {"month": "2026-04", "count": 0}]}, {"id": "finance_markets", "label": "Finance & Markets", "count": 136, "recent90d": 7, "monthly": [{"month": "2014-03", "count": 0}, {"month": "2014-04", "count": 0}, {"month": "2014-07", "count": 0}, {"month": "2014-08", "count": 0}, {"month": "2014-09", "count": 0}, {"month": "2014-10", "count": 0}, {"month": "2014-11", "count": 0}, {"month": "2014-12", "count": 0}, {"month": "2015-01", "count": 0}, {"month": "2015-03", "count": 0}, {"month": "2015-10", "count": 0}, {"month": "2015-11", "count": 0}, {"month": "2015-12", "count": 0}, {"month": "2016-01", "count": 0}, {"month": "2016-02", "count": 0}, {"month": "2016-04", "count": 0}, {"month": "2016-05", "count": 0}, {"month": "2016-06", "count": 0}, {"month": "2016-07", "count": 0}, {"month": "2016-08", "count": 0}, {"month": "2016-09", "count": 0}, {"month": "2016-10", "count": 0}, {"month": "2016-11", "count": 0}, {"month": "2016-12", "count": 0}, {"month": "2017-01", "count": 0}, {"month": "2017-02", "count": 0}, {"month": "2017-03", "count": 0}, {"month": "2017-04", "count": 0}, {"month": "2017-05", "count": 0}, {"month": "2017-06", "count": 0}, {"month": "2017-07", "count": 0}, {"month": "2017-08", "count": 0}, {"month": "2017-09", "count": 0}, {"month": "2017-10", "count": 0}, {"month": "2017-11", "count": 0}, {"month": "2017-12", "count": 0}, {"month": "2022-04", "count": 0}, {"month": "2023-05", "count": 0}, {"month": "2023-06", "count": 0}, {"month": "2023-07", "count": 0}, {"month": "2023-08", "count": 0}, {"month": "2024-04", "count": 1}, {"month": "2024-05", "count": 12}, {"month": "2024-06", "count": 8}, {"month": "2024-07", "count": 6}, {"month": "2024-08", "count": 18}, {"month": "2024-09", "count": 15}, {"month": "2024-10", "count": 8}, {"month": "2024-11", "count": 3}, {"month": "2024-12", "count": 5}, {"month": "2025-01", "count": 3}, {"month": "2025-02", "count": 8}, {"month": "2025-03", "count": 6}, {"month": "2025-04", "count": 5}, {"month": "2025-05", "count": 0}, {"month": "2025-06", "count": 1}, {"month": "2025-07", "count": 1}, {"month": "2025-08", "count": 5}, {"month": "2025-09", "count": 3}, {"month": "2025-10", "count": 12}, {"month": "2025-11", "count": 6}, {"month": "2025-12", "count": 2}, {"month": "2026-01", "count": 4}, {"month": "2026-02", "count": 2}, {"month": "2026-03", "count": 2}, {"month": "2026-04", "count": 0}]}, {"id": "cooking", "label": "Cooking", "count": 70, "recent90d": 17, "monthly": [{"month": "2014-03", "count": 0}, {"month": "2014-04", "count": 0}, {"month": "2014-07", "count": 0}, {"month": "2014-08", "count": 0}, {"month": "2014-09", "count": 0}, {"month": "2014-10", "count": 0}, {"month": "2014-11", "count": 0}, {"month": "2014-12", "count": 0}, {"month": "2015-01", "count": 0}, {"month": "2015-03", "count": 0}, {"month": "2015-10", "count": 0}, {"month": "2015-11", "count": 0}, {"month": "2015-12", "count": 0}, {"month": "2016-01", "count": 0}, {"month": "2016-02", "count": 0}, {"month": "2016-04", "count": 0}, {"month": "2016-05", "count": 0}, {"month": "2016-06", "count": 0}, {"month": "2016-07", "count": 0}, {"month": "2016-08", "count": 0}, {"month": "2016-09", "count": 0}, {"month": "2016-10", "count": 0}, {"month": "2016-11", "count": 0}, {"month": "2016-12", "count": 0}, {"month": "2017-01", "count": 0}, {"month": "2017-02", "count": 0}, {"month": "2017-03", "count": 0}, {"month": "2017-04", "count": 0}, {"month": "2017-05", "count": 0}, {"month": "2017-06", "count": 0}, {"month": "2017-07", "count": 0}, {"month": "2017-08", "count": 0}, {"month": "2017-09", "count": 0}, {"month": "2017-10", "count": 0}, {"month": "2017-11", "count": 0}, {"month": "2017-12", "count": 0}, {"month": "2022-04", "count": 0}, {"month": "2023-05", "count": 0}, {"month": "2023-06", "count": 0}, {"month": "2023-07", "count": 0}, {"month": "2023-08", "count": 1}, {"month": "2024-04", "count": 1}, {"month": "2024-05", "count": 4}, {"month": "2024-06", "count": 1}, {"month": "2024-07", "count": 0}, {"month": "2024-08", "count": 2}, {"month": "2024-09", "count": 0}, {"month": "2024-10", "count": 1}, {"month": "2024-11", "count": 2}, {"month": "2024-12", "count": 5}, {"month": "2025-01", "count": 2}, {"month": "2025-02", "count": 1}, {"month": "2025-03", "count": 1}, {"month": "2025-04", "count": 2}, {"month": "2025-05", "count": 0}, {"month": "2025-06", "count": 0}, {"month": "2025-07", "count": 5}, {"month": "2025-08", "count": 9}, {"month": "2025-09", "count": 4}, {"month": "2025-10", "count": 8}, {"month": "2025-11", "count": 0}, {"month": "2025-12", "count": 2}, {"month": "2026-01", "count": 9}, {"month": "2026-02", "count": 5}, {"month": "2026-03", "count": 4}, {"month": "2026-04", "count": 1}]}, {"id": "travel_docs", "label": "Travel / Documentaries", "count": 10, "recent90d": 3, "monthly": [{"month": "2014-03", "count": 0}, {"month": "2014-04", "count": 0}, {"month": "2014-07", "count": 0}, {"month": "2014-08", "count": 0}, {"month": "2014-09", "count": 0}, {"month": "2014-10", "count": 0}, {"month": "2014-11", "count": 0}, {"month": "2014-12", "count": 0}, {"month": "2015-01", "count": 0}, {"month": "2015-03", "count": 0}, {"month": "2015-10", "count": 0}, {"month": "2015-11", "count": 0}, {"month": "2015-12", "count": 0}, {"month": "2016-01", "count": 0}, {"month": "2016-02", "count": 0}, {"month": "2016-04", "count": 0}, {"month": "2016-05", "count": 0}, {"month": "2016-06", "count": 0}, {"month": "2016-07", "count": 0}, {"month": "2016-08", "count": 0}, {"month": "2016-09", "count": 0}, {"month": "2016-10", "count": 0}, {"month": "2016-11", "count": 0}, {"month": "2016-12", "count": 0}, {"month": "2017-01", "count": 0}, {"month": "2017-02", "count": 0}, {"month": "2017-03", "count": 0}, {"month": "2017-04", "count": 0}, {"month": "2017-05", "count": 0}, {"month": "2017-06", "count": 0}, {"month": "2017-07", "count": 0}, {"month": "2017-08", "count": 0}, {"month": "2017-09", "count": 0}, {"month": "2017-10", "count": 0}, {"month": "2017-11", "count": 0}, {"month": "2017-12", "count": 0}, {"month": "2022-04", "count": 0}, {"month": "2023-05", "count": 0}, {"month": "2023-06", "count": 0}, {"month": "2023-07", "count": 0}, {"month": "2023-08", "count": 0}, {"month": "2024-04", "count": 0}, {"month": "2024-05", "count": 0}, {"month": "2024-06", "count": 0}, {"month": "2024-07", "count": 0}, {"month": "2024-08", "count": 1}, {"month": "2024-09", "count": 1}, {"month": "2024-10", "count": 0}, {"month": "2024-11", "count": 0}, {"month": "2024-12", "count": 0}, {"month": "2025-01", "count": 0}, {"month": "2025-02", "count": 0}, {"month": "2025-03", "count": 0}, {"month": "2025-04", "count": 1}, {"month": "2025-05", "count": 1}, {"month": "2025-06", "count": 0}, {"month": "2025-07", "count": 1}, {"month": "2025-08", "count": 0}, {"month": "2025-09", "count": 0}, {"month": "2025-10", "count": 1}, {"month": "2025-11", "count": 0}, {"month": "2025-12", "count": 0}, {"month": "2026-01", "count": 2}, {"month": "2026-02", "count": 0}, {"month": "2026-03", "count": 2}, {"month": "2026-04", "count": 0}]}, {"id": "fitness_health", "label": "Fitness & Health", "count": 7, "recent90d": 1, "monthly": [{"month": "2014-03", "count": 0}, {"month": "2014-04", "count": 0}, {"month": "2014-07", "count": 0}, {"month": "2014-08", "count": 0}, {"month": "2014-09", "count": 0}, {"month": "2014-10", "count": 0}, {"month": "2014-11", "count": 0}, {"month": "2014-12", "count": 0}, {"month": "2015-01", "count": 0}, {"month": "2015-03", "count": 0}, {"month": "2015-10", "count": 0}, {"month": "2015-11", "count": 0}, {"month": "2015-12", "count": 0}, {"month": "2016-01", "count": 0}, {"month": "2016-02", "count": 0}, {"month": "2016-04", "count": 0}, {"month": "2016-05", "count": 0}, {"month": "2016-06", "count": 0}, {"month": "2016-07", "count": 0}, {"month": "2016-08", "count": 0}, {"month": "2016-09", "count": 0}, {"month": "2016-10", "count": 0}, {"month": "2016-11", "count": 0}, {"month": "2016-12", "count": 0}, {"month": "2017-01", "count": 0}, {"month": "2017-02", "count": 0}, {"month": "2017-03", "count": 0}, {"month": "2017-04", "count": 0}, {"month": "2017-05", "count": 0}, {"month": "2017-06", "count": 0}, {"month": "2017-07", "count": 0}, {"month": "2017-08", "count": 0}, {"month": "2017-09", "count": 0}, {"month": "2017-10", "count": 0}, {"month": "2017-11", "count": 0}, {"month": "2017-12", "count": 0}, {"month": "2022-04", "count": 0}, {"month": "2023-05", "count": 0}, {"month": "2023-06", "count": 0}, {"month": "2023-07", "count": 0}, {"month": "2023-08", "count": 0}, {"month": "2024-04", "count": 0}, {"month": "2024-05", "count": 0}, {"month": "2024-06", "count": 0}, {"month": "2024-07", "count": 1}, {"month": "2024-08", "count": 0}, {"month": "2024-09", "count": 1}, {"month": "2024-10", "count": 0}, {"month": "2024-11", "count": 0}, {"month": "2024-12", "count": 1}, {"month": "2025-01", "count": 0}, {"month": "2025-02", "count": 0}, {"month": "2025-03", "count": 0}, {"month": "2025-04", "count": 1}, {"month": "2025-05", "count": 0}, {"month": "2025-06", "count": 1}, {"month": "2025-07", "count": 1}, {"month": "2025-08", "count": 0}, {"month": "2025-09", "count": 0}, {"month": "2025-10", "count": 0}, {"month": "2025-11", "count": 0}, {"month": "2025-12", "count": 0}, {"month": "2026-01", "count": 0}, {"month": "2026-02", "count": 1}, {"month": "2026-03", "count": 0}, {"month": "2026-04", "count": 0}]}, {"id": "python_tools", "label": "Python Tooling", "count": 1, "recent90d": 0, "monthly": [{"month": "2014-03", "count": 0}, {"month": "2014-04", "count": 0}, {"month": "2014-07", "count": 0}, {"month": "2014-08", "count": 0}, {"month": "2014-09", "count": 0}, {"month": "2014-10", "count": 0}, {"month": "2014-11", "count": 0}, {"month": "2014-12", "count": 0}, {"month": "2015-01", "count": 0}, {"month": "2015-03", "count": 0}, {"month": "2015-10", "count": 0}, {"month": "2015-11", "count": 0}, {"month": "2015-12", "count": 0}, {"month": "2016-01", "count": 0}, {"month": "2016-02", "count": 0}, {"month": "2016-04", "count": 0}, {"month": "2016-05", "count": 0}, {"month": "2016-06", "count": 0}, {"month": "2016-07", "count": 0}, {"month": "2016-08", "count": 0}, {"month": "2016-09", "count": 0}, {"month": "2016-10", "count": 0}, {"month": "2016-11", "count": 0}, {"month": "2016-12", "count": 0}, {"month": "2017-01", "count": 0}, {"month": "2017-02", "count": 0}, {"month": "2017-03", "count": 0}, {"month": "2017-04", "count": 0}, {"month": "2017-05", "count": 0}, {"month": "2017-06", "count": 0}, {"month": "2017-07", "count": 0}, {"month": "2017-08", "count": 0}, {"month": "2017-09", "count": 0}, {"month": "2017-10", "count": 0}, {"month": "2017-11", "count": 0}, {"month": "2017-12", "count": 0}, {"month": "2022-04", "count": 0}, {"month": "2023-05", "count": 0}, {"month": "2023-06", "count": 0}, {"month": "2023-07", "count": 0}, {"month": "2023-08", "count": 0}, {"month": "2024-04", "count": 0}, {"month": "2024-05", "count": 0}, {"month": "2024-06", "count": 0}, {"month": "2024-07", "count": 0}, {"month": "2024-08", "count": 0}, {"month": "2024-09", "count": 0}, {"month": "2024-10", "count": 1}, {"month": "2024-11", "count": 0}, {"month": "2024-12", "count": 0}, {"month": "2025-01", "count": 0}, {"month": "2025-02", "count": 0}, {"month": "2025-03", "count": 0}, {"month": "2025-04", "count": 0}, {"month": "2025-05", "count": 0}, {"month": "2025-06", "count": 0}, {"month": "2025-07", "count": 0}, {"month": "2025-08", "count": 0}, {"month": "2025-09", "count": 0}, {"month": "2025-10", "count": 0}, {"month": "2025-11", "count": 0}, {"month": "2025-12", "count": 0}, {"month": "2026-01", "count": 0}, {"month": "2026-02", "count": 0}, {"month": "2026-03", "count": 0}, {"month": "2026-04", "count": 0}]}], "topChannelsByCluster": {"other": [{"name": "(no channel)", "count": 1025}, {"name": "大海去旅行", "count": 89}, {"name": "千游阁主 Wushu Traveler", "count": 78}, {"name": "丹牛食", "count": 77}, {"name": "音樂安利站 Beats Music", "count": 71}, {"name": "悦耳音乐酱", "count": 66}, {"name": "Bravos Research", "count": 66}, {"name": "贝拉聊财金", "count": 66}, {"name": "Hua Hua", "count": 61}, {"name": "Liang Dong", "count": 55}], "chinese_pop_music": [{"name": "Zhang Bichen - Topic", "count": 1120}, {"name": "Jay Chou - Topic", "count": 975}, {"name": "G.E.M. - Topic", "count": 630}, {"name": "Sun Yanzi - Topic", "count": 571}, {"name": "Release - Topic", "count": 554}, {"name": "JJ Lin - Topic", "count": 312}, {"name": "Shan Yi Chun - Topic", "count": 281}, {"name": "Hebe Tien - Topic", "count": 266}, {"name": "Mayday - Topic", "count": 236}, {"name": "Mao Buyi - Topic", "count": 163}], "ml_ai": [{"name": "Stanford Online", "count": 105}, {"name": "Andrej Karpathy", "count": 103}, {"name": "Google DeepMind", "count": 58}, {"name": "Steve Brunton", "count": 40}, {"name": "Yannic Kilcher", "count": 37}, {"name": "最佳拍档", "count": 22}, {"name": "Hung-yi Lee", "count": 21}, {"name": "Jia-Bin Huang", "count": 17}, {"name": "美投侃新闻", "count": 16}, {"name": "Outlier", "count": 16}], "chinese_news_commentary": [{"name": "美投侃新闻", "count": 200}, {"name": "王志安", "count": 137}, {"name": "IC实验室", "count": 86}, {"name": "政经鲁社长", "count": 31}, {"name": "财经风云", "count": 18}, {"name": "不想上班的小林", "count": 13}, {"name": "小岛大浪吹-非正经政经频道", "count": 13}, {"name": "阳光财经", "count": 8}, {"name": "财经不眠姐", "count": 3}, {"name": "猴哥财经 | HG Finance", "count": 3}], "cooking": [{"name": "G先生的日本旅居生活vlog", "count": 7}, {"name": "里歐愛旅遊 leolovetravel", "count": 4}, {"name": "2A夫妻", "count": 3}, {"name": "大海去旅行", "count": 3}, {"name": "尚食厨房 ShangshiKitchen", "count": 3}, {"name": "丹牛食", "count": 2}, {"name": "yuzhu time", "count": 2}, {"name": "腾讯视频 - 纪录片 - Get the WeTV APP", "count": 2}, {"name": "China Zone - 纪录片", "count": 2}, {"name": "Yunaty日本語", "count": 2}], "travel_docs": [{"name": "FINAiUS", "count": 2}, {"name": "Little Chinese Everywhere", "count": 1}, {"name": "Yul Daze", "count": 1}, {"name": "ddddddh", "count": 1}, {"name": "Riri Travels", "count": 1}, {"name": "ZongZi", "count": 1}, {"name": "Google", "count": 1}, {"name": "YOUKU DOCUMENTARY-Get APP now", "count": 1}, {"name": "Explorist", "count": 1}], "chinese_variety_tv": [{"name": "浙江卫视音乐频道 ZJSTV Music Channel - 欢迎订阅 -", "count": 86}, {"name": "天赐的声音 The Treasured Voice Official Channel", "count": 20}, {"name": "湖南卫视芒果TV官方频道  China HunanTV Official Channel", "count": 12}, {"name": "芒果TV音乐 MangoTV Music", "count": 8}, {"name": "中国好声音官方频道SING!CHINA Official Channel", "count": 7}, {"name": "YOUKU SHOW-Get APP now", "count": 5}, {"name": "综艺巨霸", "count": 4}, {"name": "Edu Tainment", "count": 3}, {"name": "iQIYI 潮综艺 - Get the iQIYI APP", "count": 3}, {"name": "综艺放映厅", "count": 2}], "scientific_computing": [{"name": "Steve Brunton", "count": 160}, {"name": "Enthought", "count": 11}, {"name": "3Blue1Brown", "count": 1}, {"name": "DeepLearningAI", "count": 1}], "kids_family": [{"name": "Like Nastya", "count": 124}, {"name": "Sheriff Labrador - Kids Cartoon", "count": 70}, {"name": "BabyBus - Kids Songs and Cartoons", "count": 22}, {"name": "寶寶巴士 - 中文兒歌童謠 - 卡通動畫", "count": 20}, {"name": "Danny Go!", "count": 14}, {"name": "Like Nastya Collections", "count": 11}, {"name": "Like Nastya Show", "count": 10}, {"name": "Like Nastya GB", "count": 8}, {"name": "Yoga Guppy", "count": 4}, {"name": "Like Nastya PRT", "count": 3}], "cpp_systems": [{"name": "Mike Shah", "count": 178}, {"name": "CppCon", "count": 40}, {"name": "The Cherno", "count": 29}, {"name": "Meeting Cpp", "count": 9}, {"name": "Hua Hua", "count": 9}, {"name": "C++ Weekly With Jason Turner", "count": 8}, {"name": "Nick", "count": 4}, {"name": "Coding Interview Prep", "count": 4}, {"name": "Anish Rao", "count": 3}, {"name": "Varteta Learning Platform", "count": 3}], "finance_markets": [{"name": "CNBC", "count": 20}, {"name": "Bloomberg Television", "count": 16}, {"name": "Bloomberg Originals", "count": 15}, {"name": "Bravos Research", "count": 10}, {"name": "CNBC Television", "count": 10}, {"name": "CNBC Make It", "count": 10}, {"name": "Bloomberg Technology", "count": 6}, {"name": "Bloomberg Podcasts", "count": 4}, {"name": "CNBC International", "count": 3}, {"name": "The Plain Bagel", "count": 3}], "fitness_health": [{"name": "The Diary Of A CEO", "count": 1}, {"name": "老佳和老萌", "count": 1}, {"name": "Yoga Guppy", "count": 1}, {"name": "EddieStyles", "count": 1}, {"name": "Leo & Jas diaries", "count": 1}, {"name": "MyHealthyDish", "count": 1}, {"name": "The Gainz Center", "count": 1}], "python_tools": [{"name": "mCoding", "count": 1}]}, "topChannelsOverall": [{"name": "Zhang Bichen - Topic", "count": 1120, "cluster": "chinese_pop_music"}, {"name": "(no channel)", "count": 1026, "cluster": "other"}, {"name": "Jay Chou - Topic", "count": 975, "cluster": "chinese_pop_music"}, {"name": "G.E.M. - Topic", "count": 630, "cluster": "chinese_pop_music"}, {"name": "Sun Yanzi - Topic", "count": 571, "cluster": "chinese_pop_music"}, {"name": "Release - Topic", "count": 554, "cluster": "chinese_pop_music"}, {"name": "JJ Lin - Topic", "count": 312, "cluster": "chinese_pop_music"}, {"name": "Shan Yi Chun - Topic", "count": 281, "cluster": "chinese_pop_music"}, {"name": "Hebe Tien - Topic", "count": 266, "cluster": "chinese_pop_music"}, {"name": "Mayday - Topic", "count": 236, "cluster": "chinese_pop_music"}, {"name": "浙江卫视音乐频道 ZJSTV Music Channel - 欢迎订阅 -", "count": 229, "cluster": "chinese_pop_music"}, {"name": "美投侃新闻", "count": 216, "cluster": "chinese_news_commentary"}, {"name": "Steve Brunton", "count": 200, "cluster": "scientific_computing"}, {"name": "Mike Shah", "count": 178, "cluster": "cpp_systems"}, {"name": "Mao Buyi - Topic", "count": 163, "cluster": "chinese_pop_music"}, {"name": "Steve Chou - Topic", "count": 153, "cluster": "chinese_pop_music"}, {"name": "王志安", "count": 137, "cluster": "chinese_news_commentary"}, {"name": "Faye Wong - Topic", "count": 125, "cluster": "chinese_pop_music"}, {"name": "Like Nastya", "count": 124, "cluster": "kids_family"}, {"name": "Stanford Online", "count": 105, "cluster": "ml_ai"}, {"name": "Andrej Karpathy", "count": 103, "cluster": "ml_ai"}, {"name": "大海去旅行", "count": 92, "cluster": "other"}, {"name": "IC实验室", "count": 87, "cluster": "chinese_news_commentary"}, {"name": "Rene Liu - Topic", "count": 86, "cluster": "chinese_pop_music"}, {"name": "丹牛食", "count": 79, "cluster": "other"}, {"name": "Eason Chan - Topic", "count": 79, "cluster": "chinese_pop_music"}, {"name": "千游阁主 Wushu Traveler", "count": 78, "cluster": "other"}, {"name": "悦耳音乐酱", "count": 77, "cluster": "other"}, {"name": "Bravos Research", "count": 76, "cluster": "other"}, {"name": "汪苏泷   - Topic", "count": 72, "cluster": "chinese_pop_music"}], "allChannels": [{"name": "Zhang Bichen - Topic", "count": 1120, "recent90d": 124, "cluster": "chinese_pop_music"}, {"name": "(no channel)", "count": 1026, "recent90d": 23, "cluster": "other"}, {"name": "Jay Chou - Topic", "count": 975, "recent90d": 197, "cluster": "chinese_pop_music"}, {"name": "G.E.M. - Topic", "count": 630, "recent90d": 101, "cluster": "chinese_pop_music"}, {"name": "Sun Yanzi - Topic", "count": 571, "recent90d": 123, "cluster": "chinese_pop_music"}, {"name": "Release - Topic", "count": 554, "recent90d": 87, "cluster": "chinese_pop_music"}, {"name": "JJ Lin - Topic", "count": 312, "recent90d": 39, "cluster": "chinese_pop_music"}, {"name": "Shan Yi Chun - Topic", "count": 281, "recent90d": 15, "cluster": "chinese_pop_music"}, {"name": "Hebe Tien - Topic", "count": 266, "recent90d": 15, "cluster": "chinese_pop_music"}, {"name": "Mayday - Topic", "count": 236, "recent90d": 26, "cluster": "chinese_pop_music"}, {"name": "浙江卫视音乐频道 ZJSTV Music Channel - 欢迎订阅 -", "count": 229, "recent90d": 14, "cluster": "chinese_pop_music"}, {"name": "美投侃新闻", "count": 216, "recent90d": 25, "cluster": "chinese_news_commentary"}, {"name": "Steve Brunton", "count": 200, "recent90d": 27, "cluster": "scientific_computing"}, {"name": "Mike Shah", "count": 178, "recent90d": 1, "cluster": "cpp_systems"}, {"name": "Mao Buyi - Topic", "count": 163, "recent90d": 17, "cluster": "chinese_pop_music"}, {"name": "Steve Chou - Topic", "count": 153, "recent90d": 7, "cluster": "chinese_pop_music"}, {"name": "王志安", "count": 137, "recent90d": 32, "cluster": "chinese_news_commentary"}, {"name": "Faye Wong - Topic", "count": 125, "recent90d": 35, "cluster": "chinese_pop_music"}, {"name": "Like Nastya", "count": 124, "recent90d": 0, "cluster": "kids_family"}, {"name": "Stanford Online", "count": 105, "recent90d": 2, "cluster": "ml_ai"}, {"name": "Andrej Karpathy", "count": 103, "recent90d": 0, "cluster": "ml_ai"}, {"name": "大海去旅行", "count": 92, "recent90d": 0, "cluster": "other"}, {"name": "IC实验室", "count": 87, "recent90d": 30, "cluster": "chinese_news_commentary"}, {"name": "Rene Liu - Topic", "count": 86, "recent90d": 12, "cluster": "chinese_pop_music"}, {"name": "丹牛食", "count": 79, "recent90d": 9, "cluster": "other"}, {"name": "Eason Chan - Topic", "count": 79, "recent90d": 15, "cluster": "chinese_pop_music"}, {"name": "千游阁主 Wushu Traveler", "count": 78, "recent90d": 2, "cluster": "other"}, {"name": "悦耳音乐酱", "count": 77, "recent90d": 42, "cluster": "other"}, {"name": "Bravos Research", "count": 76, "recent90d": 11, "cluster": "other"}, {"name": "汪苏泷   - Topic", "count": 72, "recent90d": 1, "cluster": "chinese_pop_music"}, {"name": "音樂安利站 Beats Music", "count": 71, "recent90d": 10, "cluster": "other"}, {"name": "Hua Hua", "count": 71, "recent90d": 0, "cluster": "other"}, {"name": "王赫野 - Topic", "count": 70, "recent90d": 4, "cluster": "chinese_pop_music"}, {"name": "Sheriff Labrador - Kids Cartoon", "count": 70, "recent90d": 0, "cluster": "kids_family"}, {"name": "最佳拍档", "count": 69, "recent90d": 20, "cluster": "other"}, {"name": "Aska Yang - Topic", "count": 66, "recent90d": 3, "cluster": "chinese_pop_music"}, {"name": "贝拉聊财金", "count": 66, "recent90d": 0, "cluster": "other"}, {"name": "芒果TV音乐 MangoTV Music", "count": 64, "recent90d": 13, "cluster": "other"}, {"name": "A-Lin官方專屬頻道 - Topic", "count": 64, "recent90d": 8, "cluster": "chinese_pop_music"}, {"name": "Karen Mok - Topic", "count": 63, "recent90d": 10, "cluster": "chinese_pop_music"}, {"name": "Yoga Lin - Topic", "count": 62, "recent90d": 8, "cluster": "chinese_pop_music"}, {"name": "天赐的声音 The Treasured Voice Official Channel", "count": 61, "recent90d": 8, "cluster": "chinese_pop_music"}, {"name": "Google DeepMind", "count": 58, "recent90d": 13, "cluster": "ml_ai"}, {"name": "Zhou Shen - Topic", "count": 55, "recent90d": 14, "cluster": "chinese_pop_music"}, {"name": "张碧晨资讯站-Diamond Station", "count": 55, "recent90d": 17, "cluster": "chinese_pop_music"}, {"name": "Fish Leong - Topic", "count": 55, "recent90d": 2, "cluster": "chinese_pop_music"}, {"name": "Liang Dong", "count": 55, "recent90d": 0, "cluster": "other"}, {"name": "Angela Chang - Topic", "count": 54, "recent90d": 4, "cluster": "chinese_pop_music"}, {"name": "Jane Zhang - Topic", "count": 54, "recent90d": 4, "cluster": "chinese_pop_music"}, {"name": "Lex Fridman", "count": 54, "recent90d": 12, "cluster": "other"}, {"name": "Sodagreen - Topic", "count": 51, "recent90d": 8, "cluster": "chinese_pop_music"}, {"name": "刘翔的投资频道", "count": 51, "recent90d": 8, "cluster": "other"}, {"name": "Zhang Xiaojun Podcast", "count": 49, "recent90d": 9, "cluster": "other"}, {"name": "ByteByteGo", "count": 48, "recent90d": 0, "cluster": "other"}, {"name": "中国音乐电视 Music TV", "count": 47, "recent90d": 44, "cluster": "other"}, {"name": "观鱼闲谈", "count": 47, "recent90d": 47, "cluster": "other"}, {"name": "Kenji Wu - Topic", "count": 46, "recent90d": 1, "cluster": "chinese_pop_music"}, {"name": "腾讯视频 - OST精选 - Get the WeTV APP", "count": 46, "recent90d": 0, "cluster": "other"}, {"name": "Leehom Wang - Topic", "count": 45, "recent90d": 7, "cluster": "chinese_pop_music"}, {"name": "Namewee", "count": 45, "recent90d": 13, "cluster": "other"}, {"name": "David Tao - Topic", "count": 44, "recent90d": 7, "cluster": "chinese_pop_music"}, {"name": "好叫好伐", "count": 43, "recent90d": 23, "cluster": "other"}, {"name": "周杰倫 Jay Chou", "count": 43, "recent90d": 32, "cluster": "chinese_pop_music"}, {"name": "Jannie探美国🇺🇸", "count": 43, "recent90d": 1, "cluster": "other"}, {"name": "街头小小小霸王", "count": 42, "recent90d": 2, "cluster": "other"}, {"name": "Joseph Xia", "count": 42, "recent90d": 0, "cluster": "other"}, {"name": "北美王路飞", "count": 41, "recent90d": 29, "cluster": "other"}, {"name": "姚晓棠 - Topic", "count": 41, "recent90d": 4, "cluster": "chinese_pop_music"}, {"name": "CppCon", "count": 40, "recent90d": 1, "cluster": "cpp_systems"}, {"name": "F.I.R. - Topic", "count": 40, "recent90d": 2, "cluster": "chinese_pop_music"}, {"name": "感谢订阅中剧独播", "count": 40, "recent90d": 0, "cluster": "other"}, {"name": "Lady Gaga - Topic", "count": 39, "recent90d": 25, "cluster": "chinese_pop_music"}, {"name": "大劇獨播MZTV", "count": 38, "recent90d": 0, "cluster": "other"}, {"name": "Yannic Kilcher", "count": 37, "recent90d": 1, "cluster": "ml_ai"}, {"name": "小Lin说", "count": 36, "recent90d": 1, "cluster": "other"}, {"name": "胖虎Yvette", "count": 36, "recent90d": 2, "cluster": "other"}, {"name": "Jolin Tsai - Topic", "count": 35, "recent90d": 9, "cluster": "chinese_pop_music"}, {"name": "Jason Zhang - Topic", "count": 35, "recent90d": 1, "cluster": "chinese_pop_music"}, {"name": "aMEI - Topic", "count": 35, "recent90d": 6, "cluster": "chinese_pop_music"}, {"name": "小叔TV", "count": 35, "recent90d": 2, "cluster": "other"}, {"name": "Priscilla Abby 蔡恩雨", "count": 34, "recent90d": 11, "cluster": "other"}, {"name": "Eric Chou - Topic", "count": 34, "recent90d": 3, "cluster": "chinese_pop_music"}, {"name": "杨坤 - Topic", "count": 34, "recent90d": 2, "cluster": "chinese_pop_music"}, {"name": "TANK 呂建忠 - Topic", "count": 33, "recent90d": 2, "cluster": "chinese_pop_music"}, {"name": "Namewee - Topic", "count": 32, "recent90d": 32, "cluster": "chinese_pop_music"}, {"name": "Lex Clips", "count": 32, "recent90d": 4, "cluster": "other"}, {"name": "Berkeley RDI", "count": 32, "recent90d": 5, "cluster": "other"}, {"name": "沐沐学日文", "count": 32, "recent90d": 0, "cluster": "other"}, {"name": "酷看獨播劇場 - KUKAN Drama Channel", "count": 32, "recent90d": 0, "cluster": "other"}, {"name": "DeepLearningAI", "count": 32, "recent90d": 0, "cluster": "other"}, {"name": "Coldplay - Topic", "count": 31, "recent90d": 1, "cluster": "chinese_pop_music"}, {"name": "政经鲁社长", "count": 31, "recent90d": 31, "cluster": "chinese_news_commentary"}, {"name": "电影最TOP唯一官方频道", "count": 31, "recent90d": 1, "cluster": "other"}, {"name": "Viggle AI", "count": 31, "recent90d": 0, "cluster": "other"}, {"name": "于文文 - Kelly Yu - Topic", "count": 30, "recent90d": 3, "cluster": "chinese_pop_music"}, {"name": "The Cherno", "count": 30, "recent90d": 0, "cluster": "cpp_systems"}, {"name": "Taylor Swift - Topic", "count": 29, "recent90d": 27, "cluster": "chinese_pop_music"}, {"name": "Tanya Chua - Topic", "count": 29, "recent90d": 5, "cluster": "chinese_pop_music"}, {"name": "CCTV纪录", "count": 28, "recent90d": 27, "cluster": "other"}, {"name": "下饭音乐官方频道", "count": 28, "recent90d": 22, "cluster": "other"}, {"name": "Hu Xia - Topic", "count": 28, "recent90d": 4, "cluster": "chinese_pop_music"}, {"name": "课代表立正", "count": 28, "recent90d": 0, "cluster": "other"}, {"name": "FX Evolution", "count": 28, "recent90d": 0, "cluster": "other"}, {"name": "Jia-Bin Huang", "count": 27, "recent90d": 9, "cluster": "ml_ai"}, {"name": "薛之 謙 - Topic", "count": 27, "recent90d": 2, "cluster": "chinese_pop_music"}, {"name": "Y Combinator", "count": 27, "recent90d": 3, "cluster": "other"}, {"name": "Cognitive Revolution \"How AI Changes Everything\"", "count": 27, "recent90d": 0, "cluster": "other"}, {"name": "Hung-yi Lee", "count": 27, "recent90d": 0, "cluster": "ml_ai"}, {"name": "Speak English With Vanessa", "count": 27, "recent90d": 0, "cluster": "other"}, {"name": "Coldplay", "count": 26, "recent90d": 10, "cluster": "other"}, {"name": "于冬然 - Topic", "count": 26, "recent90d": 1, "cluster": "chinese_pop_music"}, {"name": "NeetCode", "count": 26, "recent90d": 0, "cluster": "other"}, {"name": "华录百納熱播劇場", "count": 26, "recent90d": 0, "cluster": "other"}, {"name": "Yisa Yu - Topic", "count": 25, "recent90d": 8, "cluster": "chinese_pop_music"}, {"name": "菲道尔 - Topic", "count": 25, "recent90d": 1, "cluster": "chinese_pop_music"}, {"name": "en - Topic", "count": 25, "recent90d": 1, "cluster": "chinese_pop_music"}, {"name": "Li Ronghao - Topic", "count": 24, "recent90d": 2, "cluster": "chinese_pop_music"}, {"name": "GEM鄧紫棋", "count": 23, "recent90d": 20, "cluster": "chinese_pop_music"}, {"name": "Serrano.Academy", "count": 23, "recent90d": 4, "cluster": "other"}, {"name": "BLACKPINRKSS", "count": 22, "recent90d": 1, "cluster": "other"}, {"name": "腾讯视频 - 纪录片 - Get the WeTV APP", "count": 22, "recent90d": 1, "cluster": "other"}, {"name": "王貳浪 - Topic", "count": 22, "recent90d": 0, "cluster": "chinese_pop_music"}, {"name": "CNBC", "count": 22, "recent90d": 0, "cluster": "finance_markets"}, {"name": "BabyBus - Kids Songs and Cartoons", "count": 22, "recent90d": 0, "cluster": "kids_family"}, {"name": "浙江音乐纯享频道", "count": 22, "recent90d": 0, "cluster": "chinese_pop_music"}, {"name": "Jiayan Xu", "count": 22, "recent90d": 0, "cluster": "other"}, {"name": "玉麒麟", "count": 21, "recent90d": 19, "cluster": "other"}, {"name": "王宇宙Leto - Topic", "count": 21, "recent90d": 3, "cluster": "chinese_pop_music"}, {"name": "MrBeast", "count": 21, "recent90d": 0, "cluster": "other"}, {"name": "Google for Developers", "count": 20, "recent90d": 17, "cluster": "ml_ai"}, {"name": "Low Budget Stories", "count": 20, "recent90d": 18, "cluster": "other"}, {"name": "艾森 Essen", "count": 20, "recent90d": 7, "cluster": "other"}, {"name": "Fox News", "count": 20, "recent90d": 7, "cluster": "other"}, {"name": "硅谷101", "count": 20, "recent90d": 4, "cluster": "other"}, {"name": "刘惜君 - Topic", "count": 20, "recent90d": 3, "cluster": "chinese_pop_music"}, {"name": "Links TV", "count": 20, "recent90d": 0, "cluster": "other"}, {"name": "Sakura Japanese Cafe", "count": 20, "recent90d": 0, "cluster": "other"}, {"name": "寶寶巴士 - 中文兒歌童謠 - 卡通動畫", "count": 20, "recent90d": 0, "cluster": "kids_family"}, {"name": "NaNa说美股", "count": 20, "recent90d": 0, "cluster": "other"}, {"name": "superex drama", "count": 19, "recent90d": 4, "cluster": "other"}, {"name": "Dr. Tracey Marks", "count": 19, "recent90d": 0, "cluster": "other"}, {"name": "Ren Ran - Topic", "count": 19, "recent90d": 0, "cluster": "chinese_pop_music"}, {"name": "UNIVERSAL MUSIC TAIWAN 環球音樂", "count": 19, "recent90d": 0, "cluster": "other"}, {"name": "Dwarkesh Patel", "count": 18, "recent90d": 4, "cluster": "other"}, {"name": "LiveNOW from FOX", "count": 18, "recent90d": 2, "cluster": "other"}, {"name": "The Diary Of A CEO", "count": 18, "recent90d": 12, "cluster": "other"}, {"name": "财经风云", "count": 18, "recent90d": 2, "cluster": "chinese_news_commentary"}, {"name": "Lemon English", "count": 18, "recent90d": 0, "cluster": "other"}, {"name": "美投讲美股", "count": 18, "recent90d": 0, "cluster": "other"}, {"name": "新官场", "count": 17, "recent90d": 4, "cluster": "other"}, {"name": "南拳媽媽 - Topic", "count": 17, "recent90d": 3, "cluster": "chinese_pop_music"}, {"name": "丁噹 Della Ding - Topic", "count": 17, "recent90d": 3, "cluster": "chinese_pop_music"}, {"name": "Baby Zhang - Topic", "count": 17, "recent90d": 1, "cluster": "chinese_pop_music"}, {"name": "林隆璇 - Topic", "count": 17, "recent90d": 2, "cluster": "chinese_pop_music"}, {"name": "Umar Jamil", "count": 17, "recent90d": 1, "cluster": "ml_ai"}, {"name": "Lit Nomad", "count": 17, "recent90d": 1, "cluster": "other"}, {"name": "Shannon Chou 湾区地产经纪人 服务旧金山湾区 硅谷房产买卖 诚信可靠", "count": 17, "recent90d": 0, "cluster": "other"}, {"name": "安全警長啦咘啦哆-兒童動畫", "count": 17, "recent90d": 0, "cluster": "other"}, {"name": "Outlier", "count": 17, "recent90d": 0, "cluster": "ml_ai"}, {"name": "官场", "count": 17, "recent90d": 0, "cluster": "other"}, {"name": "和有风一起学习无货源跨境电商", "count": 17, "recent90d": 0, "cluster": "other"}, {"name": "freeCodeCamp.org", "count": 17, "recent90d": 0, "cluster": "other"}, {"name": "liferoad2007", "count": 17, "recent90d": 0, "cluster": "other"}, {"name": "BitTiger官方频道 BitTiger Official Channel", "count": 17, "recent90d": 0, "cluster": "other"}, {"name": "HUNTR/X - Topic", "count": 16, "recent90d": 16, "cluster": "chinese_pop_music"}, {"name": "Li Jian - Topic", "count": 16, "recent90d": 2, "cluster": "chinese_pop_music"}, {"name": "Bloomberg Originals", "count": 16, "recent90d": 2, "cluster": "finance_markets"}, {"name": "5566 - Topic", "count": 16, "recent90d": 2, "cluster": "chinese_pop_music"}, {"name": "Bloomberg Television", "count": 16, "recent90d": 1, "cluster": "finance_markets"}, {"name": "Shusen Wang", "count": 16, "recent90d": 0, "cluster": "other"}, {"name": "承桓 - Topic", "count": 16, "recent90d": 0, "cluster": "chinese_pop_music"}, {"name": "S.H.E - Topic", "count": 16, "recent90d": 0, "cluster": "chinese_pop_music"}, {"name": "MZTV Exclusive Chinese Drama", "count": 16, "recent90d": 0, "cluster": "other"}, {"name": "YuBin", "count": 15, "recent90d": 15, "cluster": "other"}, {"name": "La Jiao - Topic", "count": 15, "recent90d": 3, "cluster": "chinese_pop_music"}, {"name": "小白的奇幻旅行", "count": 15, "recent90d": 14, "cluster": "other"}, {"name": "小钟Johnny", "count": 15, "recent90d": 6, "cluster": "other"}, {"name": "OpenAI", "count": 15, "recent90d": 2, "cluster": "ml_ai"}, {"name": "Pieter Abbeel", "count": 15, "recent90d": 0, "cluster": "other"}, {"name": "YouTube Movies", "count": 14, "recent90d": 9, "cluster": "other"}, {"name": "CCTV中国中央电视台", "count": 14, "recent90d": 2, "cluster": "other"}, {"name": "希林娜依·高 - Topic", "count": 14, "recent90d": 1, "cluster": "chinese_pop_music"}, {"name": "Faye Wong Official Channel", "count": 14, "recent90d": 1, "cluster": "chinese_pop_music"}, {"name": "石羽彤 - Topic", "count": 14, "recent90d": 9, "cluster": "chinese_pop_music"}, {"name": "Arxiv Insights", "count": 14, "recent90d": 4, "cluster": "other"}, {"name": "向思思 - Topic", "count": 14, "recent90d": 1, "cluster": "chinese_pop_music"}, {"name": "张哥人在江湖", "count": 14, "recent90d": 5, "cluster": "other"}, {"name": "DRAMA JAPAN", "count": 14, "recent90d": 0, "cluster": "other"}, {"name": "冷水TV・日本生活與日本文化", "count": 14, "recent90d": 0, "cluster": "other"}, {"name": "Welch Labs", "count": 14, "recent90d": 0, "cluster": "ml_ai"}, {"name": "北卡房产-华华", "count": 14, "recent90d": 0, "cluster": "other"}, {"name": "美国之音中文网", "count": 14, "recent90d": 0, "cluster": "other"}, {"name": "Danny Go!", "count": 14, "recent90d": 0, "cluster": "kids_family"}, {"name": "陈冰 - Topic", "count": 14, "recent90d": 0, "cluster": "chinese_pop_music"}, {"name": "Jam Hsiao - Topic", "count": 14, "recent90d": 0, "cluster": "chinese_pop_music"}, {"name": "一目十影", "count": 14, "recent90d": 0, "cluster": "other"}, {"name": "张雪峰考研考公说", "count": 14, "recent90d": 0, "cluster": "other"}, {"name": "不想上班的小林", "count": 13, "recent90d": 12, "cluster": "chinese_news_commentary"}, {"name": "Fireship", "count": 13, "recent90d": 2, "cluster": "other"}, {"name": "小岛大浪吹-非正经政经频道", "count": 13, "recent90d": 2, "cluster": "chinese_news_commentary"}]}